tradeo/__init__.py
tradeo/bash/launch-mt5.sh
tradeo/bash/stop-mt.sh
tradeo/blocker.py
tradeo/config.py
tradeo/data/.gitkeep
tradeo/event_handlers/__init__.py
tradeo/event_handlers/basic_event_handler.py
tradeo/event_handlers/event_handler.py
tradeo/executable/basic_forex.py
tradeo/executable/executable.py
tradeo/files.py
tradeo/log.py
tradeo/mt_client.py
tradeo/mt_message.py
tradeo/mt_tb_expert.mq5
tradeo/ohlc.py
tradeo/order.py
tradeo/order_operations.py
tradeo/order_type.py
tradeo/paths.py
tradeo/singleton.py
tradeo/strategies/__init__.py
tradeo/strategies/basic_strategy.py
tradeo/strategies/strategy.py
tradeo/trading_methods.py
tradeo/utils.py
tradeo-0.23.1.dist-info/LICENSE
tradeo-0.23.1.dist-info/METADATA
tradeo-0.23.1.dist-info/WHEEL
tradeo-0.23.1.dist-info/RECORD
