Metadata-Version: 2.3
Name: tradeo
Version: 0.23.1
Summary: This library contains a series of tools to create a trading bot for Forex trading using Metatrader.
License: MIT
Keywords: trading,forex,metatrader,bot,investment,finance,trading-bot,trading-strategy
Author: Cayetano Romero Vargas
Author-email: cromerovargas2d@gmail.com
Requires-Python: >=3.10.0
Classifier: Development Status :: 4 - Beta
Classifier: Intended Audience :: Developers
Classifier: Programming Language :: Python :: 3.10
Classifier: Programming Language :: Python :: 3.11
Classifier: Programming Language :: Python :: 3.12
Classifier: Programming Language :: Python :: 3.13
Classifier: Topic :: Software Development :: Libraries :: Python Modules
Classifier: Topic :: Office/Business :: Financial :: Investment
Classifier: Topic :: Office/Business :: Financial :: Accounting
Classifier: Topic :: Office/Business :: Financial
Requires-Dist: pandas (>=2.2.3,<3.0.0)
Requires-Dist: psutil (>=6.1.0,<7.0.0)
Requires-Dist: pytz (>=2024.2,<2025.0)
Requires-Dist: requests (>=2.32.3,<3.0.0)
Project-URL: Changelog, https://github.com/sorul/tradeo/blob/master/CHANGELOG.md
Project-URL: Repository, https://github.com/sorul/tradeo
